phonexia_transcription_normalization_client.py
phonexia_transcription_normalization_client-1.0.2.dist-info/METADATA
phonexia_transcription_normalization_client-1.0.2.dist-info/WHEEL
phonexia_transcription_normalization_client-1.0.2.dist-info/entry_points.txt
phonexia_transcription_normalization_client-1.0.2.dist-info/top_level.txt
phonexia_transcription_normalization_client-1.0.2.dist-info/RECORD
