Metadata-Version: 2.4
Name: phonexia-transcription-normalization-client
Version: 1.0.2
Summary: Transcription Normalization Client
Keywords: grpc,stt,speech-to-text,text,transcription,normalization
Requires-Python: >=3.9
Requires-Dist: more-itertools>=10.6.0
Requires-Dist: phonexia-grpc>=2.16.2
